scrapy_zen/__init__.py
scrapy_zen/addons.py
scrapy_zen/contracts.py
scrapy_zen/databases.py
scrapy_zen/dupefilters.py
scrapy_zen/extensions.py
scrapy_zen/handler.py
scrapy_zen/logging.py
scrapy_zen/middlewares.py
scrapy_zen/monitors.py
scrapy_zen/pipelines.py
scrapy_zen/schemas/news.json
scrapy_zen/templates/message.jinja
scrapy_zen/utils.py
scrapy_zen-1.0.4.dist-info/METADATA
scrapy_zen-1.0.4.dist-info/WHEEL
scrapy_zen-1.0.4.dist-info/RECORD
