Metadata-Version: 2.3
Name: scrapy-zen
Version: 1.0.4
Summary: 
Author: Ehsan U.
Author-email: lancerf562@gmail.com
Requires-Python: >=3.12
Classifier: Programming Language :: Python :: 3
Classifier: Programming Language :: Python :: 3.12
Classifier: Programming Language :: Python :: 3.13
Provides-Extra: all
Provides-Extra: browserforge
Provides-Extra: girgit
Provides-Extra: grpc
Provides-Extra: monitoring
Provides-Extra: playwright
Provides-Extra: websocket
Provides-Extra: zyte
Requires-Dist: browserforge[all] ; extra == "browserforge"
Requires-Dist: dateparser
Requires-Dist: grpcio ; extra == "all"
Requires-Dist: grpcio ; extra == "grpc"
Requires-Dist: html-text
Requires-Dist: jsonpath-ng
Requires-Dist: logparser ; extra == "all"
Requires-Dist: logparser ; extra == "monitoring"
Requires-Dist: protobuf ; extra == "all"
Requires-Dist: protobuf ; extra == "grpc"
Requires-Dist: python-dotenv
Requires-Dist: redis[hiredis]
Requires-Dist: scrapy
Requires-Dist: scrapy-girgit ; extra == "all"
Requires-Dist: scrapy-girgit ; extra == "girgit"
Requires-Dist: scrapy-playwright ; extra == "all"
Requires-Dist: scrapy-playwright ; extra == "playwright"
Requires-Dist: scrapy-zyte-api ; extra == "all"
Requires-Dist: scrapy-zyte-api ; extra == "zyte"
Requires-Dist: spidermon[monitoring] ; extra == "all"
Requires-Dist: spidermon[monitoring] ; extra == "monitoring"
Requires-Dist: websockets ; extra == "all"
Requires-Dist: websockets ; extra == "websocket"
